kcommand/__init__.py
kcommand/command.py
kcommand-0.1.0.0.dist-info/licenses/LICENSE
kcommand-0.1.0.0.dist-info/METADATA
kcommand-0.1.0.0.dist-info/WHEEL
kcommand-0.1.0.0.dist-info/top_level.txt
kcommand-0.1.0.0.dist-info/RECORD
