Metadata-Version: 2.4
Name: kcommand
Version: 0.1.0.0
Summary: KCommand
Home-page: https://github.com/kokaito-git/kcommand
Author: kokaito-git
Author-email: kokaito.git@gmail.com
Classifier: Programming Language :: Python :: 3
Classifier: Operating System :: OS Independent
Classifier: Operating System :: Microsoft :: Windows
Classifier: Operating System :: MacOS
Classifier: Operating System :: POSIX :: Linux
Classifier: License :: OSI Approved :: MIT License
Requires-Python: >=3.13
License-File: LICENSE
Requires-Dist: kmodels
Dynamic: author
Dynamic: author-email
Dynamic: classifier
Dynamic: home-page
Dynamic: license-file
Dynamic: requires-dist
Dynamic: requires-python
Dynamic: summary
